<?xml version="1.0" encoding="UTF-8" ?>
<!DOCTYPE mapper PUBLIC "-//mybatis.org//DTD Mapper 3.0//EN" "http://mybatis.org/dtd/mybatis-3-mapper.dtd" >
<mapper namespace="com.xiben.pm.tk.mapper.TkTasknodeMapper" >
  <resultMap id="BaseResultMap" type="com.xiben.pm.tk.pojo.TkTasknode" >
    <!--
      WARNING - @mbggenerated
      This element is automatically generated by MyBatis Generator, do not modify.
      This element was generated on Tue Nov 21 09:04:33 CST 2017.
    -->
    <id column="nodeid" property="nodeid" jdbcType="INTEGER" />
    <result column="compid" property="compid" jdbcType="INTEGER" />
    <result column="deptid" property="deptid" jdbcType="INTEGER" />
    <result column="taskid" property="taskid" jdbcType="INTEGER" />
    <result column="type" property="type" jdbcType="INTEGER" />
    <result column="remark" property="remark" jdbcType="VARCHAR" />
    <result column="score" property="score" jdbcType="INTEGER" />
    <result column="createby" property="createby" jdbcType="INTEGER" />
    <result column="createdate" property="createdate" jdbcType="TIMESTAMP" />
    <result column="updateby" property="updateby" jdbcType="INTEGER" />
    <result column="updatedate" property="updatedate" jdbcType="TIMESTAMP" />
  </resultMap>
  <sql id="Example_Where_Clause" >
    <!--
      WARNING - @mbggenerated
      This element is automatically generated by MyBatis Generator, do not modify.
      This element was generated on Tue Nov 21 09:04:33 CST 2017.
    -->
    <where >
      <foreach collection="oredCriteria" item="criteria" separator="or" >
        <if test="criteria.valid" >
          <trim prefix="(" suffix=")" prefixOverrides="and" >
            <foreach collection="criteria.criteria" item="criterion" >
              <choose >
                <when test="criterion.noValue" >
                  and ${criterion.condition}
                </when>
                <when test="criterion.singleValue" >
                  and ${criterion.condition} #{criterion.value}
                </when>
                <when test="criterion.betweenValue" >
                  and ${criterion.condition} #{criterion.value} and #{criterion.secondValue}
                </when>
                <when test="criterion.listValue" >
                  and ${criterion.condition}
                  <foreach collection="criterion.value" item="listItem" open="(" close=")" separator="," >
                    #{listItem}
                  </foreach>
                </when>
              </choose>
            </foreach>
          </trim>
        </if>
      </foreach>
    </where>
  </sql>
  <sql id="Update_By_Example_Where_Clause" >
    <!--
      WARNING - @mbggenerated
      This element is automatically generated by MyBatis Generator, do not modify.
      This element was generated on Tue Nov 21 09:04:33 CST 2017.
    -->
    <where >
      <foreach collection="example.oredCriteria" item="criteria" separator="or" >
        <if test="criteria.valid" >
          <trim prefix="(" suffix=")" prefixOverrides="and" >
            <foreach collection="criteria.criteria" item="criterion" >
              <choose >
                <when test="criterion.noValue" >
                  and ${criterion.condition}
                </when>
                <when test="criterion.singleValue" >
                  and ${criterion.condition} #{criterion.value}
                </when>
                <when test="criterion.betweenValue" >
                  and ${criterion.condition} #{criterion.value} and #{criterion.secondValue}
                </when>
                <when test="criterion.listValue" >
                  and ${criterion.condition}
                  <foreach collection="criterion.value" item="listItem" open="(" close=")" separator="," >
                    #{listItem}
                  </foreach>
                </when>
              </choose>
            </foreach>
          </trim>
        </if>
      </foreach>
    </where>
  </sql>
  <sql id="Base_Column_List" >
    <!--
      WARNING - @mbggenerated
      This element is automatically generated by MyBatis Generator, do not modify.
      This element was generated on Tue Nov 21 09:04:33 CST 2017.
    -->
    nodeid, compid, deptid, taskid, type, remark, score, createby, createdate, updateby, 
    updatedate
  </sql>
  <select id="selectByExample" resultMap="BaseResultMap" parameterType="com.xiben.pm.tk.pojo.TkTasknodeExample" >
    <!--
      WARNING - @mbggenerated
      This element is automatically generated by MyBatis Generator, do not modify.
      This element was generated on Tue Nov 21 09:04:33 CST 2017.
    -->
    select
    <if test="distinct" >
      distinct
    </if>
    <include refid="Base_Column_List" />
    from tk_tasknode
    <if test="_parameter != null" >
      <include refid="Example_Where_Clause" />
    </if>
    <if test="orderByClause != null" >
      order by ${orderByClause}
    </if>
  </select>
  <select id="selectByPrimaryKey" resultMap="BaseResultMap" parameterType="java.lang.Integer" >
    <!--
      WARNING - @mbggenerated
      This element is automatically generated by MyBatis Generator, do not modify.
      This element was generated on Tue Nov 21 09:04:33 CST 2017.
    -->
    select 
    <include refid="Base_Column_List" />
    from tk_tasknode
    where nodeid = #{nodeid,jdbcType=INTEGER}
  </select>
  <delete id="deleteByPrimaryKey" parameterType="java.lang.Integer" >
    <!--
      WARNING - @mbggenerated
      This element is automatically generated by MyBatis Generator, do not modify.
      This element was generated on Tue Nov 21 09:04:33 CST 2017.
    -->
    delete from tk_tasknode
    where nodeid = #{nodeid,jdbcType=INTEGER}
  </delete>
  <delete id="deleteByExample" parameterType="com.xiben.pm.tk.pojo.TkTasknodeExample" >
    <!--
      WARNING - @mbggenerated
      This element is automatically generated by MyBatis Generator, do not modify.
      This element was generated on Tue Nov 21 09:04:33 CST 2017.
    -->
    delete from tk_tasknode
    <if test="_parameter != null" >
      <include refid="Example_Where_Clause" />
    </if>
  </delete>
  <insert id="insert" useGeneratedKeys="true" keyProperty="nodeid" parameterType="com.xiben.pm.tk.pojo.TkTasknode" >
    <!--
      WARNING - @mbggenerated
      This element is automatically generated by MyBatis Generator, do not modify.
      This element was generated on Tue Nov 21 09:04:33 CST 2017.
    -->
    insert into tk_tasknode ( compid, deptid, 
      taskid, type, remark, 
      score, createby, createdate, 
      updateby, updatedate)
    values ( #{compid,jdbcType=INTEGER}, #{deptid,jdbcType=INTEGER}, 
      #{taskid,jdbcType=INTEGER}, #{type,jdbcType=INTEGER}, #{remark,jdbcType=VARCHAR}, 
      #{score,jdbcType=INTEGER}, #{createby,jdbcType=INTEGER}, #{createdate,jdbcType=TIMESTAMP}, 
      #{updateby,jdbcType=INTEGER}, #{updatedate,jdbcType=TIMESTAMP})
  </insert>
  <insert id="insertSelective" parameterType="com.xiben.pm.tk.pojo.TkTasknode" >
    <!--
      WARNING - @mbggenerated
      This element is automatically generated by MyBatis Generator, do not modify.
      This element was generated on Tue Nov 21 09:04:33 CST 2017.
    -->
    insert into tk_tasknode
    <trim prefix="(" suffix=")" suffixOverrides="," >
      <if test="nodeid != null" >
        nodeid,
      </if>
      <if test="compid != null" >
        compid,
      </if>
      <if test="deptid != null" >
        deptid,
      </if>
      <if test="taskid != null" >
        taskid,
      </if>
      <if test="type != null" >
        type,
      </if>
      <if test="remark != null" >
        remark,
      </if>
      <if test="score != null" >
        score,
      </if>
      <if test="createby != null" >
        createby,
      </if>
      <if test="createdate != null" >
        createdate,
      </if>
      <if test="updateby != null" >
        updateby,
      </if>
      <if test="updatedate != null" >
        updatedate,
      </if>
    </trim>
    <trim prefix="values (" suffix=")" suffixOverrides="," >
      <if test="nodeid != null" >
        #{nodeid,jdbcType=INTEGER},
      </if>
      <if test="compid != null" >
        #{compid,jdbcType=INTEGER},
      </if>
      <if test="deptid != null" >
        #{deptid,jdbcType=INTEGER},
      </if>
      <if test="taskid != null" >
        #{taskid,jdbcType=INTEGER},
      </if>
      <if test="type != null" >
        #{type,jdbcType=INTEGER},
      </if>
      <if test="remark != null" >
        #{remark,jdbcType=VARCHAR},
      </if>
      <if test="score != null" >
        #{score,jdbcType=INTEGER},
      </if>
      <if test="createby != null" >
        #{createby,jdbcType=INTEGER},
      </if>
      <if test="createdate != null" >
        #{createdate,jdbcType=TIMESTAMP},
      </if>
      <if test="updateby != null" >
        #{updateby,jdbcType=INTEGER},
      </if>
      <if test="updatedate != null" >
        #{updatedate,jdbcType=TIMESTAMP},
      </if>
    </trim>
  </insert>
  <select id="countByExample" parameterType="com.xiben.pm.tk.pojo.TkTasknodeExample" resultType="java.lang.Integer" >
    <!--
      WARNING - @mbggenerated
      This element is automatically generated by MyBatis Generator, do not modify.
      This element was generated on Tue Nov 21 09:04:33 CST 2017.
    -->
    select count(*) from tk_tasknode
    <if test="_parameter != null" >
      <include refid="Example_Where_Clause" />
    </if>
  </select>
  <update id="updateByExampleSelective" parameterType="map" >
    <!--
      WARNING - @mbggenerated
      This element is automatically generated by MyBatis Generator, do not modify.
      This element was generated on Tue Nov 21 09:04:33 CST 2017.
    -->
    update tk_tasknode
    <set >
      <if test="record.nodeid != null" >
        nodeid = #{record.nodeid,jdbcType=INTEGER},
      </if>
      <if test="record.compid != null" >
        compid = #{record.compid,jdbcType=INTEGER},
      </if>
      <if test="record.deptid != null" >
        deptid = #{record.deptid,jdbcType=INTEGER},
      </if>
      <if test="record.taskid != null" >
        taskid = #{record.taskid,jdbcType=INTEGER},
      </if>
      <if test="record.type != null" >
        type = #{record.type,jdbcType=INTEGER},
      </if>
      <if test="record.remark != null" >
        remark = #{record.remark,jdbcType=VARCHAR},
      </if>
      <if test="record.score != null" >
        score = #{record.score,jdbcType=INTEGER},
      </if>
      <if test="record.createby != null" >
        createby = #{record.createby,jdbcType=INTEGER},
      </if>
      <if test="record.createdate != null" >
        createdate = #{record.createdate,jdbcType=TIMESTAMP},
      </if>
      <if test="record.updateby != null" >
        updateby = #{record.updateby,jdbcType=INTEGER},
      </if>
      <if test="record.updatedate != null" >
        updatedate = #{record.updatedate,jdbcType=TIMESTAMP},
      </if>
    </set>
    <if test="_parameter != null" >
      <include refid="Update_By_Example_Where_Clause" />
    </if>
  </update>
  <update id="updateByExample" parameterType="map" >
    <!--
      WARNING - @mbggenerated
      This element is automatically generated by MyBatis Generator, do not modify.
      This element was generated on Tue Nov 21 09:04:33 CST 2017.
    -->
    update tk_tasknode
    set nodeid = #{record.nodeid,jdbcType=INTEGER},
      compid = #{record.compid,jdbcType=INTEGER},
      deptid = #{record.deptid,jdbcType=INTEGER},
      taskid = #{record.taskid,jdbcType=INTEGER},
      type = #{record.type,jdbcType=INTEGER},
      remark = #{record.remark,jdbcType=VARCHAR},
      score = #{record.score,jdbcType=INTEGER},
      createby = #{record.createby,jdbcType=INTEGER},
      createdate = #{record.createdate,jdbcType=TIMESTAMP},
      updateby = #{record.updateby,jdbcType=INTEGER},
      updatedate = #{record.updatedate,jdbcType=TIMESTAMP}
    <if test="_parameter != null" >
      <include refid="Update_By_Example_Where_Clause" />
    </if>
  </update>
  <update id="updateByPrimaryKeySelective" parameterType="com.xiben.pm.tk.pojo.TkTasknode" >
    <!--
      WARNING - @mbggenerated
      This element is automatically generated by MyBatis Generator, do not modify.
      This element was generated on Tue Nov 21 09:04:33 CST 2017.
    -->
    update tk_tasknode
    <set >
      <if test="compid != null" >
        compid = #{compid,jdbcType=INTEGER},
      </if>
      <if test="deptid != null" >
        deptid = #{deptid,jdbcType=INTEGER},
      </if>
      <if test="taskid != null" >
        taskid = #{taskid,jdbcType=INTEGER},
      </if>
      <if test="type != null" >
        type = #{type,jdbcType=INTEGER},
      </if>
      <if test="remark != null" >
        remark = #{remark,jdbcType=VARCHAR},
      </if>
      <if test="score != null" >
        score = #{score,jdbcType=INTEGER},
      </if>
      <if test="createby != null" >
        createby = #{createby,jdbcType=INTEGER},
      </if>
      <if test="createdate != null" >
        createdate = #{createdate,jdbcType=TIMESTAMP},
      </if>
      <if test="updateby != null" >
        updateby = #{updateby,jdbcType=INTEGER},
      </if>
      <if test="updatedate != null" >
        updatedate = #{updatedate,jdbcType=TIMESTAMP},
      </if>
    </set>
    where nodeid = #{nodeid,jdbcType=INTEGER}
  </update>
  <update id="updateByPrimaryKey" parameterType="com.xiben.pm.tk.pojo.TkTasknode" >
    <!--
      WARNING - @mbggenerated
      This element is automatically generated by MyBatis Generator, do not modify.
      This element was generated on Tue Nov 21 09:04:33 CST 2017.
    -->
    update tk_tasknode
    set compid = #{compid,jdbcType=INTEGER},
      deptid = #{deptid,jdbcType=INTEGER},
      taskid = #{taskid,jdbcType=INTEGER},
      type = #{type,jdbcType=INTEGER},
      remark = #{remark,jdbcType=VARCHAR},
      score = #{score,jdbcType=INTEGER},
      createby = #{createby,jdbcType=INTEGER},
      createdate = #{createdate,jdbcType=TIMESTAMP},
      updateby = #{updateby,jdbcType=INTEGER},
      updatedate = #{updatedate,jdbcType=TIMESTAMP}
    where nodeid = #{nodeid,jdbcType=INTEGER}
  </update>
</mapper>